LICENSE
MANIFEST.in
README.rst
setup.py
django_ops/__init__.py
django_ops/admin.py
django_ops/apps.py
django_ops/log_views.py
django_ops/migration_util.py
django_ops/mixins.py
django_ops/models.py
django_ops/redis_views.py
django_ops/routines.py
django_ops/serializers.py
django_ops/share.py
django_ops/tasks.py
django_ops/tests.py
django_ops/urls.py
django_ops/utilities.py
django_ops/views.py
django_ops.egg-info/PKG-INFO
django_ops.egg-info/SOURCES.txt
django_ops.egg-info/dependency_links.txt
django_ops.egg-info/requires.txt
django_ops.egg-info/top_level.txt
django_ops/management/__init__.py
django_ops/management/commands/__init__.py
django_ops/management/commands/run_archive.py
django_ops/management/commands/run_housekeep.py
django_ops/management/commands/run_ops_routines.py
django_ops/migrations/0001_initial.py
django_ops/migrations/0002_auto_20201016_1127.py
django_ops/migrations/__init__.py